pipelib/__init__.py
pipelib/logger.py
pipelib/pipeline.py
pipelib/version.py
pipelib/pipelines/__init__.py
pipelib/pipelines/container.py
pipelib/pipelines/git.py
pipelib/steps/__init__.py
pipelib/steps/step.py
pipelib/steps/container/__init__.py
pipelib/steps/container/tags.py
pipelib/steps/filters/__init__.py
pipelib/steps/filters/git.py
pipelib/steps/filters/numeric.py
pipelib/steps/filters/strings.py
pipelib/steps/release/__init__.py
pipelib/steps/release/tags.py
pipelib/steps/sort/__init__.py
pipelib/steps/sort/basic.py
pipelib/steps/transform/__init__.py
pipelib/steps/transform/numeric.py
pipelib/steps/transform/strings.py
pipelib/tests/__init__.py
pipelib/tests/helpers.py
pipelib/tests/test_pipelines.py
pipelib/tests/test_steps.py
pipelib/tests/test_utils.py
pipelib/tests/test_wrappers.py
pipelib/utils/__init__.py
pipelib/utils/docs.py
pipelib/utils/fileio.py
pipelib/utils/inspect.py
pipelib/utils/terminal.py
pipelib/wrappers/__init__.py
pipelib/wrappers/base.py
pipelib/wrappers/version.py
pipelib-0.0.17.dist-info/LICENSE
pipelib-0.0.17.dist-info/METADATA
pipelib-0.0.17.dist-info/WHEEL
pipelib-0.0.17.dist-info/top_level.txt
pipelib-0.0.17.dist-info/RECORD
